medico/__init__.py
medico-1.2.dist-info/METADATA
medico-1.2.dist-info/WHEEL
medico-1.2.dist-info/top_level.txt
medico-1.2.dist-info/RECORD
