Metadata-Version: 2.1
Name: medico
Version: 1.2
Summary: Extract vital medical information from text.
Author: Mr. Medico
Requires-Dist: boto3
Requires-Dist: spacy
Requires-Dist: nltk
